cdk_auth/__init__.py
cdk_auth/py.typed
cdk_auth/_jsii/__init__.py
cdk_auth/_jsii/cdk-auth@0.0.5.jsii.tgz
cdk_auth-0.0.5.dist-info/LICENSE
cdk_auth-0.0.5.dist-info/METADATA
cdk_auth-0.0.5.dist-info/WHEEL
cdk_auth-0.0.5.dist-info/top_level.txt
cdk_auth-0.0.5.dist-info/RECORD
