Metadata-Version: 2.1
Name: cdk-auth
Version: 0.0.5
Summary: A construct that adds additional auth features to Cognito
Home-page: https://github.com/chris/cdk-auth.git
Author: Chris Finn<chris@finnternet.com>
License: MIT
Project-URL: Source, https://github.com/chris/cdk-auth.git
Platform: UNKNOWN
Classifier: Intended Audience :: Developers
Classifier: Operating System :: OS Independent
Classifier: Programming Language :: JavaScript
Classifier: Programming Language :: Python :: 3 :: Only
Classifier: Programming Language :: Python :: 3.6
Classifier: Programming Language :: Python :: 3.7
Classifier: Programming Language :: Python :: 3.8
Classifier: Programming Language :: Python :: 3.9
Classifier: Typing :: Typed
Classifier: Development Status :: 5 - Production/Stable
Classifier: License :: OSI Approved
Requires-Python: >=3.6
License-File: LICENSE
Requires-Dist: aws-cdk-lib (<3.0.0,>=2.1.0)
Requires-Dist: constructs (<11.0.0,>=10.0.5)
Requires-Dist: jsii (<2.0.0,>=1.55.1)
Requires-Dist: publication (>=0.0.3)
